{
  "usesTypeScript": true,
  "usesCssModule": false,
  "testLibrary": "None",
  "cssPreprocessor": "scss",
  "component": {
    "default": {
      "path": "src/components",
      "withStyle": false,
      "withTest": false,
      "withLazy": false,
      "withStyled": true,
      "withIndex": true,
      "withTypeDeclare": true,
      "customTemplates": {
        "index": ".templates/component/index.ts",
        "component": ".templates/component/TemplateName.tsx",
        "typeDeclare": ".templates/component/TemplateName.d.ts",
        "styled": ".templates/component/styled.ts"
      },
      "withStory": false
    }
  }
}
